bok_choy/__init__.py
bok_choy/browser.py
bok_choy/javascript.py
bok_choy/page_object.py
bok_choy/promise.py
bok_choy/query.py
bok_choy/web_app_test.py
bok_choy/a11y/__init__.py
bok_choy/a11y/a11y_audit.py
bok_choy/a11y/axe_core_ruleset.py
bok_choy/a11y/axs_ruleset.py
bok_choy/vendor/axe-core/axe.min.js
bok_choy/vendor/google/axs_testing.js
bok_choy-2.0.2.dist-info/AUTHORS
bok_choy-2.0.2.dist-info/LICENSE.txt
bok_choy-2.0.2.dist-info/METADATA
bok_choy-2.0.2.dist-info/NOTICE.txt
bok_choy-2.0.2.dist-info/WHEEL
bok_choy-2.0.2.dist-info/top_level.txt
bok_choy-2.0.2.dist-info/RECORD
