Metadata-Version: 2.1
Name: bok-choy
Version: 2.0.2
Summary: Deprecated UI-level acceptance test framework
Home-page: http://github.com/openedx/bok-choy
Author: edX
Author-email: oscm@edx.org
License: Apache 2.0
Classifier: Development Status :: 7 - Inactive
Classifier: Environment :: Console
Classifier: Intended Audience :: Developers
Classifier: License :: OSI Approved :: Apache Software License
Classifier: Operating System :: OS Independent
Classifier: Programming Language :: Python
Classifier: Programming Language :: Python :: 3
Classifier: Programming Language :: Python :: 3.8
Classifier: Programming Language :: Python :: Implementation :: CPython
Classifier: Programming Language :: Python :: Implementation :: PyPy
Classifier: Topic :: Software Development :: Testing
Classifier: Topic :: Software Development :: Quality Assurance
License-File: LICENSE.txt
License-File: NOTICE.txt
License-File: AUTHORS
Requires-Dist: lazy
Requires-Dist: selenium (<4,>=2)
Provides-Extra: visual_diff
Requires-Dist: needle ; extra == 'visual_diff'
